oopa-2.0.1.data/scripts/oopa
oopa_base/__init__.py
oopa_base/analysis.py
oopa_base/table.py
oopa_base/modules/__init__.py
oopa_base/modules/charset.py
oopa_base/modules/keyword.py
oopa_base/modules/length.py
oopa_base/modules/mask.py
oopa-2.0.1.dist-info/METADATA
oopa-2.0.1.dist-info/WHEEL
oopa-2.0.1.dist-info/top_level.txt
oopa-2.0.1.dist-info/RECORD
