Metadata-Version: 2.1
Name: oopa
Version: 2.0.1
Summary: A script that dumps stats on a wordlist for password research
Home-page: https://www.axolotl-logic.io/
Author: Axolotl-Logic
Author-email: me@axolotl-logic.io
Requires-Dist: prettytable
